{
    "task":  "auto_commit",
    "status":  "ok",
    "path":  "C:\\Users\\19766\\.openclaw\\workspace\\self-evolution-log",
    "summary":  "commit created and pushed with verified remote alignment",
    "timestamp":  "2026-03-13T01:32:34.4799021+08:00",
    "details":  {
                    "branch":  "main",
                    "verify":  "matched",
                    "head":  "5dcd1f5ffa6264c74355a5c3d01427037958d21f",
                    "originUrl":  "https://github.com/ydx0214/openclaw.git",
                    "remote":  "origin/main",
                    "changed":  true
                }
}
